.DS_Store
pyarchy/__init__.py
pyarchy/_version.py
pyarchy/common.py
pyarchy/core.py
pyarchy/data.py
pyarchy/events.py
pyarchy/mechanical.py
pyarchy/meta.py
pyarchy/utils.py
pyarchy-1.2.0.dist-info/DESCRIPTION.rst
pyarchy-1.2.0.dist-info/METADATA
pyarchy-1.2.0.dist-info/RECORD
pyarchy-1.2.0.dist-info/WHEEL
pyarchy-1.2.0.dist-info/metadata.json
pyarchy-1.2.0.dist-info/top_level.txt
