Metadata-Version: 2.0
Name: pyarchy
Version: 1.2.0
Summary: A collection of object management tools
Home-page: https://github.com/zachgates/pyarchy
Author: Zach Gates
Author-email: thezachgates@gmail.com
License: MIT
Platform: UNKNOWN
Classifier: License :: OSI Approved :: MIT License
Classifier: Programming Language :: Python :: 3
Classifier: Programming Language :: Python :: 3.3
Classifier: Programming Language :: Python :: 3.4
Classifier: Programming Language :: Python :: 3.5
Classifier: Programming Language :: Python :: 3.6
